minimcp_servers/__init__.py
minimcp_servers/core/builder.py
minimcp_servers/core/logger.py
minimcp_servers/modules/datetime.py
minimcp_servers/modules/random_generator.py
minimcp_servers/modules/text.py
minimcp_servers/modules/math/arithmetic.py
minimcp_servers/modules/math/continuous.py
minimcp_servers/modules/math/discrete.py
minimcp_servers/modules/math/stats.py
minimcp_servers/servers/arithmetic_math_utils.py
minimcp_servers/servers/continuous_math_utils.py
minimcp_servers/servers/datetime_utils.py
minimcp_servers/servers/discrete_math_utils.py
minimcp_servers/servers/math_utils.py
minimcp_servers/servers/random_generator.py
minimcp_servers/servers/statistics_math_utils.py
minimcp_servers/servers/text_utils.py
minimcp_servers-0.3.0.dist-info/METADATA
minimcp_servers-0.3.0.dist-info/WHEEL
minimcp_servers-0.3.0.dist-info/entry_points.txt
minimcp_servers-0.3.0.dist-info/licenses/LICENSE
minimcp_servers-0.3.0.dist-info/RECORD
