Metadata-Version: 2.4
Name: minimcp-servers
Version: 0.3.0
Summary: MCP servers built with MiniMCP to expose Python’s standard library modules.
Project-URL: Repository, https://github.com/sreenaths/minimcp-servers
Project-URL: PyPI, https://pypi.org/project/minimcp-servers/
Author-email: Sreenath Somarajapuram <somarajapuram@gmail.com>
License:                                  Apache License
License-File: LICENSE
Classifier: Framework :: AsyncIO
Classifier: License :: OSI Approved :: Apache Software License
Classifier: Programming Language :: Python :: 3
Classifier: Programming Language :: Python :: 3.10
Classifier: Programming Language :: Python :: 3.11
Classifier: Programming Language :: Python :: 3.12
Classifier: Topic :: Software Development :: Libraries
Requires-Python: >=3.10
Requires-Dist: minimcp==0.4.1
